{
  "updated": "2026-03-21T13:35:15.183111+00:00",
  "source": "miamimusicweek.com",
  "new_events_count": 42,
  "new_events": [
    {
      "url": "https://miamimusicweek.com/event/factory-town-music-week-day-1",
      "name": "Factory Town Music Week (Day 1)",
      "date": "Mar 25",
      "venue": ">",
      "artists": ">"
    },
    {
      "url": "https://miamimusicweek.com/event/brobot-records-miami-x-we-group-hi-fi",
      "name": "Brobot Records Miami x We Group Hi-Fi",
      "date": "Mar 24",
      "venue": ">",
      "artists": ">"
    },
    {
      "url": "https://miamimusicweek.com/event/experts-only-miami-music-week-2026",
      "name": "Experts Only: Miami Music Week 2026",
      "date": "Mar 24",
      "venue": ">",
      "artists": ">"
    },
    {
      "url": "https://miamimusicweek.com/event/satoshi-tomiie-melody-more-nomad-talent-mmw-opener",
      "name": "Satoshi Tomiie, Melody &amp; More (NOMAD Talent MMW Opener)",
      "date": "Mar 24",
      "venue": ">",
      "artists": ">"
    },
    {
      "url": "https://miamimusicweek.com/event/fsq-funk-style-quality",
      "name": "FSQ (FUNK STYLE QUALITY)",
      "date": "Mar 24",
      "venue": ">",
      "artists": ">"
    },
    {
      "url": "https://miamimusicweek.com/event/that-thing-on-wednesday-hoh-x-enjoy-x-vice-city",
      "name": "That Thing on Wednesday - HoH x ENJOY x Vice City",
      "date": "Mar 24",
      "venue": ">",
      "artists": ">"
    },
    {
      "url": "https://miamimusicweek.com/event/get-closer-luuk-van-dijk",
      "name": "Get Closer: Luuk Van Dijk",
      "date": "Mar 24",
      "venue": ">",
      "artists": ">"
    },
    {
      "url": "https://miamimusicweek.com/event/monrroe-sustance-mmw",
      "name": "Monrroe + Sustance MMW",
      "date": "Mar 24",
      "venue": ">",
      "artists": ">"
    },
    {
      "url": "https://miamimusicweek.com/event/crystal-waters-i-am-house-orchestrated",
      "name": "I Am House Orchestrated by Crystal Waters",
      "date": "Mar 25",
      "venue": ">",
      "artists": ">"
    },
    {
      "url": "https://miamimusicweek.com/event/benjamin-lloyd-miami-music-week-at-e11even",
      "name": "MIAMI MUSIC WEEK AT E11EVEN: BENJAMIN LLOYD",
      "date": "Mar 24",
      "venue": ">",
      "artists": ">"
    },
    {
      "url": "https://miamimusicweek.com/event/beatport-live-pool-party-x-20-years-rekids",
      "name": "Beatport Live Pool Party x 20 Years Rekids",
      "date": "Mar 24",
      "venue": ">",
      "artists": ">"
    },
    {
      "url": "https://miamimusicweek.com/event/20five8records-x-groovemates",
      "name": "20Five8Records x Groovemates",
      "date": "Mar 24",
      "venue": ">",
      "artists": ">"
    },
    {
      "url": "https://miamimusicweek.com/event/ultra-music-festival-2026-day-2",
      "name": "Ultra Music Festival 2026 (Day 2)",
      "date": "Mar 24",
      "venue": ">",
      "artists": ">"
    },
    {
      "url": "https://miamimusicweek.com/event/balance-miami",
      "name": "Balance Miami",
      "date": "Mar 25",
      "venue": ">",
      "artists": ">"
    },
    {
      "url": "https://miamimusicweek.com/event/boris-brejcha-miss-monique-resistance-mmw",
      "name": "Boris Brejcha, Miss Monique: RESISTANCE MMW",
      "date": "Mar 28",
      "venue": ">",
      "artists": ">"
    },
    {
      "url": "https://miamimusicweek.com/event/grvdgr",
      "name": "GRAVDGR",
      "date": "Mar 24",
      "venue": ">",
      "artists": ">"
    },
    {
      "url": "https://miamimusicweek.com/event/hugel-s-make-the-girls-dance-miami-music-week-2026",
      "name": "Hugel&#39;s Make The Girls Dance: Miami Music Week 2026",
      "date": "Mar 24",
      "venue": ">",
      "artists": ">"
    },
    {
      "url": "https://miamimusicweek.com/event/cheetah-print-rafael",
      "name": "Cheetah Print: Rafael",
      "date": "Mar 24",
      "venue": ">",
      "artists": ">"
    },
    {
      "url": "https://miamimusicweek.com/event/carl-cox-maceo-plex-resistance-mmw-closing-party",
      "name": "Carl Cox, Maceo Plex - RESISTANCE MMW Closing Party",
      "date": "Mar 29",
      "venue": ">",
      "artists": ">"
    },
    {
      "url": "https://miamimusicweek.com/event/welcome-to-miami-music-week",
      "name": "Welcome to Miami Music Week",
      "date": "Mar 24",
      "venue": ">",
      "artists": ">"
    },
    {
      "url": "https://miamimusicweek.com/event/mmw26-ben-bohmer-live",
      "name": "MMW26: BEN B\u00d6HMER LIVE",
      "date": "Mar 24",
      "venue": ">",
      "artists": ">"
    },
    {
      "url": "https://miamimusicweek.com/event/incorrect-music-showcase-mmw-2026",
      "name": "Incorrect Music Showcase (MMW 2026)",
      "date": "Mar 25",
      "venue": ">",
      "artists": ">"
    },
    {
      "url": "https://miamimusicweek.com/event/ultra-music-festival-2026",
      "name": "Ultra Music Festival 2026 (Day 1)",
      "date": "Mar 24",
      "venue": ">",
      "artists": ">"
    },
    {
      "url": "https://miamimusicweek.com/event/coldharbour-night-mmw",
      "name": "Coldharbour Night (MMW)",
      "date": "Mar 24",
      "venue": ">",
      "artists": ">"
    },
    {
      "url": "https://miamimusicweek.com/event/the-hideout-presents-something-light-showcase",
      "name": "The Hideout presents Something Light Showcase",
      "date": "Mar 24",
      "venue": ">",
      "artists": ">"
    },
    {
      "url": "https://miamimusicweek.com/event/eric-prydz-argy-jeremy-olander-resistance-mmw",
      "name": "Eric Prydz, Argy, Jeremy Olander: RESISTANCE MMW",
      "date": "Mar 26",
      "venue": ">",
      "artists": ">"
    },
    {
      "url": "https://miamimusicweek.com/event/amelie-lens-boys-noize-otta-resistance-mmw",
      "name": "Amelie Lens, Boys Noize, \u00d8TTA: RESISTANCE MMW",
      "date": "Mar 27",
      "venue": ">",
      "artists": ">"
    },
    {
      "url": "https://miamimusicweek.com/event/ultra-music-festival-2026-day-3",
      "name": "Ultra Music Festival 2026 (Day 3)",
      "date": "Mar 24",
      "venue": ">",
      "artists": ">"
    },
    {
      "url": "https://miamimusicweek.com/event/mmw-at-mad-radio-musumeci-israel-sunshine",
      "name": "MMW AT MAD RADIO: Musumeci, Israel Sunshine",
      "date": "Mar 24",
      "venue": "sets the stage for a stylish yet chill night out. Whether you\u00b4re a party pro or just vibing, this is the spot.\r\nTune in our slick radio show serving up the latest tracks.\r\nSave the date and cath the urban-chic experience at Mad Radio Miami. See you on the dance floor!",
      "artists": ">"
    },
    {
      "url": "https://miamimusicweek.com/event/perreo-del-futuro-presents-six-sex-miami-music-week",
      "name": "Perreo Del Futuro Presents: Six Sex Miami Music Week",
      "date": "Mar 24",
      "venue": ">",
      "artists": ">"
    },
    {
      "url": "https://miamimusicweek.com/event/yousuke-yukimatsu-999999999-juliet-fox-resistance-mmw",
      "name": "Yousuke Yukimatsu, 999999999, Juliet Fox: RESISTANCE MMW",
      "date": "Mar 25",
      "venue": ">",
      "artists": ">"
    },
    {
      "url": "https://miamimusicweek.com/event/beatport-live-pool-party-x-mood-child",
      "name": "Beatport Live Pool Party x Mood Child",
      "date": "Mar 24",
      "venue": ">",
      "artists": ">"
    },
    {
      "url": "https://miamimusicweek.com/event/do-not-sit-on-mmw-madota-nervous-records",
      "name": "Do Not Sit On MMW : Madota [Nervous Records]",
      "date": "Mar 24",
      "venue": ">",
      "artists": ">"
    },
    {
      "url": "https://miamimusicweek.com/event/prodigy-artist-miami-music-week",
      "name": "Prodigy Artist: Miami Music Week",
      "date": "Mar 25",
      "venue": ">",
      "artists": "Miami Music Week | Miami Music Week"
    },
    {
      "url": "https://miamimusicweek.com/event/splash-revolution-pool-party",
      "name": "Splash Revolution Pool Party",
      "date": "Mar 24",
      "venue": ">",
      "artists": ">"
    },
    {
      "url": "https://miamimusicweek.com/event/subsolar-x-dtla-present-thicc-cuts-in-miami-music-week",
      "name": "Subsolar x DTLA present: Thicc Cuts in Miami Music Week",
      "date": "Mar 24",
      "venue": ">",
      "artists": ">"
    },
    {
      "url": "https://miamimusicweek.com/event/r-party-serena-rooftop",
      "name": "R PARTY - Serena Rooftop",
      "date": "Mar 24",
      "venue": ">",
      "artists": ">"
    },
    {
      "url": "https://miamimusicweek.com/event/open-channel-mmw-acraze-b2b-cid-fallon-jazzy",
      "name": "Open Channel MMW: Acraze b2b CID, Fallon, Jazzy",
      "date": "Mar 24",
      "venue": ">",
      "artists": ">"
    },
    {
      "url": "https://miamimusicweek.com/event/riordan-selects-miami-music-week",
      "name": "Riordan Selects: Miami Music Week",
      "date": "Mar 24",
      "venue": ">",
      "artists": ">"
    },
    {
      "url": "https://miamimusicweek.com/event/sagamore-pool-party-dj-mag-presents-cloonee",
      "name": "DJ Mag presents Cloonee (Sagamore Pool Party)",
      "date": "Mar 24",
      "venue": ">",
      "artists": ">"
    },
    {
      "url": "https://miamimusicweek.com/event/momentos-x-under-no-illusion-present",
      "name": "Momentos X Under No Illusion Present",
      "date": "Mar 24",
      "venue": ">",
      "artists": ">"
    },
    {
      "url": "https://miamimusicweek.com/event/miami-music-week-at-e11even-oliver-heldens",
      "name": "MIAMI MUSIC WEEK AT E11EVEN: OLIVER HELDENS",
      "date": "Mar 25",
      "venue": ">",
      "artists": ">"
    }
  ]
}