{
  "updated": "2026-03-21T23:18:42.237567+00:00",
  "source": "google_news_rss",
  "signals": {
    "1": {
      "articles": 102,
      "score": 1.0
    },
    "2": {
      "articles": 18,
      "score": 0.176
    },
    "3": {
      "articles": 19,
      "score": 0.186
    },
    "4": {
      "articles": 27,
      "score": 0.265
    },
    "5": {
      "articles": 11,
      "score": 0.108
    },
    "6": {
      "articles": 34,
      "score": 0.333
    },
    "7": {
      "articles": 61,
      "score": 0.598
    },
    "8": {
      "articles": 40,
      "score": 0.392
    },
    "9": {
      "articles": 28,
      "score": 0.275
    },
    "10": {
      "articles": 69,
      "score": 0.676
    },
    "11": {
      "articles": 75,
      "score": 0.735
    },
    "12": {
      "articles": 25,
      "score": 0.245
    },
    "13": {
      "articles": 41,
      "score": 0.402
    },
    "14": {
      "articles": 75,
      "score": 0.735
    },
    "15": {
      "articles": 23,
      "score": 0.225
    },
    "16": {
      "articles": 19,
      "score": 0.186
    },
    "17": {
      "articles": 14,
      "score": 0.137
    },
    "18": {
      "articles": 43,
      "score": 0.422
    },
    "19": {
      "articles": 15,
      "score": 0.147
    },
    "20": {
      "articles": 9,
      "score": 0.088
    },
    "21": {
      "articles": 30,
      "score": 0.294
    },
    "22": {
      "articles": 66,
      "score": 0.647
    },
    "23": {
      "articles": 88,
      "score": 0.863
    },
    "24": {
      "articles": 88,
      "score": 0.863
    },
    "25": {
      "articles": 16,
      "score": 0.157
    },
    "26": {
      "articles": 79,
      "score": 0.775
    },
    "27": {
      "articles": 82,
      "score": 0.804
    },
    "28": {
      "articles": 40,
      "score": 0.392
    },
    "29": {
      "articles": 89,
      "score": 0.873
    },
    "30": {
      "articles": 28,
      "score": 0.275
    },
    "31": {
      "articles": 58,
      "score": 0.569
    },
    "32": {
      "articles": 24,
      "score": 0.235
    },
    "33": {
      "articles": 97,
      "score": 0.951
    },
    "34": {
      "articles": 42,
      "score": 0.412
    },
    "35": {
      "articles": 24,
      "score": 0.235
    },
    "36": {
      "articles": 27,
      "score": 0.265
    },
    "37": {
      "articles": 18,
      "score": 0.176
    },
    "38": {
      "articles": 18,
      "score": 0.176
    },
    "39": {
      "articles": 85,
      "score": 0.833
    },
    "40": {
      "articles": 75,
      "score": 0.735
    },
    "41": {
      "articles": 42,
      "score": 0.412
    },
    "42": {
      "articles": 91,
      "score": 0.892
    },
    "43": {
      "articles": 60,
      "score": 0.588
    },
    "44": {
      "articles": 17,
      "score": 0.167
    },
    "45": {
      "articles": 52,
      "score": 0.51
    },
    "46": {
      "articles": 82,
      "score": 0.804
    },
    "47": {
      "articles": 93,
      "score": 0.912
    },
    "48": {
      "articles": 65,
      "score": 0.637
    },
    "49": {
      "articles": 41,
      "score": 0.402
    },
    "50": {
      "articles": 31,
      "score": 0.304
    },
    "51": {
      "articles": 60,
      "score": 0.588
    },
    "52": {
      "articles": 0,
      "score": 0.0
    },
    "53": {
      "articles": 25,
      "score": 0.245
    },
    "54": {
      "articles": 51,
      "score": 0.5
    },
    "55": {
      "articles": 19,
      "score": 0.186
    },
    "56": {
      "articles": 25,
      "score": 0.245
    },
    "57": {
      "articles": 2,
      "score": 0.02
    },
    "58": {
      "articles": 25,
      "score": 0.245
    },
    "59": {
      "articles": 35,
      "score": 0.343
    },
    "60": {
      "articles": 52,
      "score": 0.51
    },
    "61": {
      "articles": 81,
      "score": 0.794
    },
    "62": {
      "articles": 62,
      "score": 0.608
    },
    "63": {
      "articles": 61,
      "score": 0.598
    },
    "64": {
      "articles": 27,
      "score": 0.265
    },
    "65": {
      "articles": 12,
      "score": 0.118
    },
    "66": {
      "articles": 54,
      "score": 0.529
    },
    "67": {
      "articles": 91,
      "score": 0.892
    },
    "68": {
      "articles": 40,
      "score": 0.392
    },
    "69": {
      "articles": 30,
      "score": 0.294
    },
    "70": {
      "articles": 87,
      "score": 0.853
    },
    "71": {
      "articles": 63,
      "score": 0.618
    },
    "72": {
      "articles": 52,
      "score": 0.51
    },
    "73": {
      "articles": 58,
      "score": 0.569
    },
    "74": {
      "articles": 42,
      "score": 0.412
    },
    "75": {
      "articles": 20,
      "score": 0.196
    },
    "76": {
      "articles": 46,
      "score": 0.451
    },
    "77": {
      "articles": 19,
      "score": 0.186
    },
    "78": {
      "articles": 57,
      "score": 0.559
    },
    "79": {
      "articles": 32,
      "score": 0.314
    },
    "80": {
      "articles": 99,
      "score": 0.971
    },
    "81": {
      "articles": 71,
      "score": 0.696
    },
    "82": {
      "articles": 32,
      "score": 0.314
    },
    "83": {
      "articles": 92,
      "score": 0.902
    },
    "84": {
      "articles": 66,
      "score": 0.647
    },
    "85": {
      "articles": 15,
      "score": 0.147
    },
    "86": {
      "articles": 17,
      "score": 0.167
    },
    "87": {
      "articles": 24,
      "score": 0.235
    },
    "88": {
      "articles": 0,
      "score": 0.0
    },
    "89": {
      "articles": 5,
      "score": 0.049
    },
    "90": {
      "articles": 17,
      "score": 0.167
    },
    "91": {
      "articles": 23,
      "score": 0.225
    },
    "92": {
      "articles": 12,
      "score": 0.118
    },
    "93": {
      "articles": 12,
      "score": 0.118
    },
    "94": {
      "articles": 19,
      "score": 0.186
    },
    "95": {
      "articles": 13,
      "score": 0.127
    },
    "96": {
      "articles": 21,
      "score": 0.206
    },
    "97": {
      "articles": 44,
      "score": 0.431
    },
    "98": {
      "articles": 0,
      "score": 0.0
    },
    "99": {
      "articles": 0,
      "score": 0.0
    },
    "100": {
      "articles": 40,
      "score": 0.392
    },
    "101": {
      "articles": 6,
      "score": 0.059
    },
    "102": {
      "articles": 52,
      "score": 0.51
    },
    "103": {
      "articles": 12,
      "score": 0.118
    },
    "104": {
      "articles": 23,
      "score": 0.225
    },
    "105": {
      "articles": 97,
      "score": 0.951
    },
    "106": {
      "articles": 82,
      "score": 0.804
    },
    "107": {
      "articles": 98,
      "score": 0.961
    },
    "108": {
      "articles": 22,
      "score": 0.216
    },
    "109": {
      "articles": 17,
      "score": 0.167
    }
  }
}